LICENSE
MANIFEST.in
README.md
setup.py
JIMG/__init__.py
JIMG.egg-info/PKG-INFO
JIMG.egg-info/SOURCES.txt
JIMG.egg-info/dependency_links.txt
JIMG.egg-info/requires.txt
JIMG.egg-info/top_level.txt
JIMG/app/__init__.py
JIMG/app/load_app.py
JIMG/app/__pycache__/__init__.cpython-310.pyc
JIMG/app/__pycache__/__init__.cpython-312.pyc
JIMG/app/__pycache__/load_app.cpython-310.pyc
JIMG/app/__pycache__/load_app.cpython-312.pyc
JIMG/functions/__init__.py
JIMG/functions/jimg.py
JIMG/icons/jbi_icon.ico
JIMG/icons/jbi_icon.png
JIMG/icons/jbs_icon.png
test/test_run.py