Metadata-Version: 2.1
Name: JIMG
Version: 2.1.5
Summary: JIMG
Author: Jakub Kubis
Author-email: jbiosystem@gmail.com
License: MIT
Keywords: python,opera,pheoniximages,annotation,AI,cv,perkin,high-resolution
Classifier: Development Status :: 3 - Alpha
Classifier: Programming Language :: Python :: 3
Classifier: Operating System :: MacOS :: MacOS X
Classifier: Operating System :: Microsoft :: Windows
Classifier: Operating System :: POSIX :: Linux
Requires-Python: >=3.6
License-File: LICENSE
